{
  "project_info": {
    "project_number": "307419989181",
    "project_id": "flutter-bookstore-7d0d3",
    "storage_bucket": "flutter-bookstore-7d0d3.firebasestorage.app"
  },
  "client": [
    {
      "client_info": {
        "mobilesdk_app_id": "1:307419989181:android:06fb3bd07eedce6a3363d4",
        "android_client_info": {
          "package_name": "com.example.knjizara"
        }
      },
      "oauth_client": [],
      "api_key": [
        {
          "current_key": "AIzaSyBdCIL6wLCqRZtlBCBPdY6K7olKZGsnkMs"
        }
      ],
      "services": {
        "appinvite_service": {
          "other_platform_oauth_client": []
        }
      }
    }
  ],
  "configuration_version": "1"
}